[
  {
    "code": "RK-1B4ED0",
    "username": "haibungvv",
    "serverDomain": "https://rikishop.panelvripate.my.id",
    "panelDetails": {
      "ram": 1050,
      "disk": 1050,
      "cpu": 40,
      "egg": "16",
      "nestid": "5",
      "loc": "1"
    },
    "creationDate": "2025-10-13T03:39:18.855Z",
    "expiryDate": "2025-11-12T03:39:18.856Z",
    "status": "claimed",
    "claimedDate": "2025-10-13T03:51:32.069Z"
  },
  {
    "code": "RK-B57F58",
    "username": "ngetes",
    "serverDomain": "https://rikishop.panelvripate.my.id",
    "panelDetails": {
      "ram": 1050,
      "disk": 1050,
      "cpu": 40,
      "egg": "16",
      "nestid": "5",
      "loc": "1"
    },
    "creationDate": "2025-10-13T17:19:03.066Z",
    "expiryDate": "2025-11-12T17:19:03.067Z",
    "status": "active",
    "claimedDate": null
  },
  {
    "code": "RK-77DE5F",
    "username": "ngetesa",
    "serverDomain": "https://rikishop.panelvripate.my.id",
    "panelDetails": {
      "ram": 5050,
      "disk": 5050,
      "cpu": 120,
      "egg": "16",
      "nestid": "5",
      "loc": "1"
    },
    "creationDate": "2025-10-13T18:27:37.078Z",
    "expiryDate": "2025-11-12T18:27:37.079Z",
    "status": "active",
    "claimedDate": null
  },
  {
    "code": "RK-9368B1",
    "username": "literasi",
    "serverDomain": "https://rikishop.panelvripate.my.id",
    "panelDetails": {
      "ram": 1050,
      "disk": 1050,
      "cpu": 40,
      "egg": "16",
      "nestid": "5",
      "loc": "1"
    },
    "creationDate": "2025-10-13T18:55:12.282Z",
    "expiryDate": "2025-11-12T18:55:12.283Z",
    "status": "active",
    "claimedDate": null
  },
  {
    "code": "RK-2F0F4B",
    "username": "akemila",
    "serverDomain": "https://rikishop.panelvripate.my.id",
    "panelDetails": {
      "ram": 1050,
      "disk": 1050,
      "cpu": 40,
      "egg": "16",
      "nestid": "5",
      "loc": "1"
    },
    "creationDate": "2025-10-13T19:22:40.098Z",
    "panelExpiryDate": "2025-11-12T19:22:40.099Z",
    "warrantyExpiryDate": "2025-10-28T19:22:40.099Z",
    "status": "active",
    "claimedDate": null
  },
  {
    "code": "RK-842D5D",
    "username": "zall",
    "serverDomain": "https://rikishop.panelvripate.my.id",
    "panelDetails": {
      "ram": 0,
      "disk": 0,
      "cpu": 0,
      "egg": "16",
      "nestid": "5",
      "loc": "1"
    },
    "creationDate": "2025-10-14T03:03:50.066Z",
    "panelExpiryDate": "2025-11-13T03:03:50.068Z",
    "warrantyExpiryDate": "2025-10-29T03:03:50.067Z",
    "status": "active",
    "claimedDate": null
  },
  {
    "code": "RK-9FCAA0",
    "username": "abi",
    "serverDomain": "https://rikishop.panelvripate.my.id",
    "panelDetails": {
      "ram": 0,
      "disk": 0,
      "cpu": 0,
      "egg": "16",
      "nestid": "5",
      "loc": "1"
    },
    "creationDate": "2025-10-14T09:19:11.563Z",
    "panelExpiryDate": "2025-11-13T09:19:11.565Z",
    "warrantyExpiryDate": "2025-10-29T09:19:11.564Z",
    "status": "active",
    "claimedDate": null
  },
  {
    "code": "RK-572DE4",
    "username": "kzr",
    "serverDomain": "https://rikishop.panelvripate.my.id",
    "panelDetails": {
      "ram": 3050,
      "disk": 3050,
      "cpu": 80,
      "egg": "16",
      "nestid": "5",
      "loc": "1"
    },
    "creationDate": "2025-10-15T06:46:50.862Z",
    "panelExpiryDate": "2025-11-14T06:46:50.864Z",
    "warrantyExpiryDate": "2025-10-30T06:46:50.863Z",
    "status": "active",
    "claimedDate": null
  }
]